flask_liquid/__init__.py
flask_liquid/flask_liquid.py
flask_liquid/py.typed
flask_liquid-2.0.1.dist-info/METADATA
flask_liquid-2.0.1.dist-info/WHEEL
flask_liquid-2.0.1.dist-info/licenses/LICENSE
flask_liquid-2.0.1.dist-info/RECORD
