Metadata-Version: 2.4
Name: Flask-Liquid
Version: 2.0.1
Summary: A Flask extension for rendering Liquid templates.
Project-URL: Change Log, https://github.com/jg-rp/flask-liquid/blob/main/CHANGES.md
Project-URL: Documentation, https://jg-rp.github.io/liquid/guides/flask-liquid
Project-URL: Homepage, https://github.com/jg-rp/flask-liquid
Project-URL: Issue Tracker, https://github.com/jg-rp/flask-liquid/issues
Project-URL: Source Code, https://github.com/jg-rp/flask-liquid
License-Expression: MIT
License-File: LICENSE
Classifier: Development Status :: 5 - Production/Stable
Classifier: Intended Audience :: Developers
Classifier: License :: OSI Approved :: MIT License
Classifier: Programming Language :: Python :: 3
Classifier: Programming Language :: Python :: 3.10
Classifier: Programming Language :: Python :: 3.11
Classifier: Programming Language :: Python :: 3.12
Classifier: Programming Language :: Python :: 3.13
Classifier: Programming Language :: Python :: 3.14
Classifier: Programming Language :: Python :: Implementation :: CPython
Requires-Python: >=3.10
Requires-Dist: flask>=3.0
Requires-Dist: markupsafe>=3.0.0
Requires-Dist: python-liquid>=2.0.0
